datastack/__init__.py
datastack/cli.py
datastack/logger.py
datastack/util.py
datastack/connections/__inti__.py
datastack/connections/sql_connection.py
datastack/plugin/chart.py
datastack/runtime/__init__.py
datastack/runtime/runtime.py
datastack/runtime/session_manager.py
datastack/runtime/test_app.py
datastack/server/__init__.py
datastack/server/auth.py
datastack/server/caching.py
datastack/server/server.py
datastack/server/utils.py
datastack/stacker/__init__.py
datastack/stacker/stacker.py
datastack/static/3rdpartylicenses.txt
datastack/static/app.json
datastack/static/favicon.ico
datastack/static/fontawesome-webfont.2b13baa7dd4f54c9.eot
datastack/static/fontawesome-webfont.8a7cb27d142e3e19.ttf
datastack/static/fontawesome-webfont.cf011583fb81df9f.woff
datastack/static/fontawesome-webfont.da909aa098b0ee2d.svg
datastack/static/fontawesome-webfont.e9955780856cf8aa.woff2
datastack/static/index.html
datastack/static/main.020c9f41fa4720ff.js
datastack/static/main.11afc696ed4dbab6.js
datastack/static/main.13d16d16594775cf.js
datastack/static/main.2d2232b5c1b27dd9.js
datastack/static/main.430969208671e0c4.js
datastack/static/main.57f734ac51808a6f.js
datastack/static/main.81df02d8749804cb.js
datastack/static/main.84d83bf890e6ed0e.js
datastack/static/main.88fcfe7af276c704.js
datastack/static/main.af4e457d32d50c30.js
datastack/static/main.d599b004010ee349.js
datastack/static/main.de663e8d52213ef7.js
datastack/static/main.e789ec36a911277f.js
datastack/static/polyfills.dab51ea5492118af.js
datastack/static/polyfills.ed4fe3edd840e1b2.js
datastack/static/runtime.1de5c4e609b22f85.js
datastack/static/runtime.aaedba49815d2ab0.js
datastack/static/scripts.b35cb861d669039a.js
datastack/static/styles.35e2509caaf4d596.css
datastack/static/styles.e13040b928f048c1.css
pydatastack-0.0.5.data/data/static/3rdpartylicenses.txt
pydatastack-0.0.5.data/data/static/app.json
pydatastack-0.0.5.data/data/static/favicon.ico
pydatastack-0.0.5.data/data/static/fontawesome-webfont.2b13baa7dd4f54c9.eot
pydatastack-0.0.5.dist-info/METADATA
pydatastack-0.0.5.dist-info/WHEEL
pydatastack-0.0.5.dist-info/entry_points.txt
pydatastack-0.0.5.dist-info/top_level.txt
pydatastack-0.0.5.dist-info/RECORD
