Metadata-Version: 2.1
Name: pydatastack
Version: 0.0.5
Summary: The Fastes way to build apps in python
Author: Vishal Vora, Mayur Pokiya, Karan Doshi
Requires-Dist: click ==8.1.3
Requires-Dist: Flask ==2.2.2
Requires-Dist: Flask-Cors ==3.0.10
Requires-Dist: GitPython ==3.1.31
Requires-Dist: numpy
Requires-Dist: pandas
Requires-Dist: plotly ==5.14.0
Requires-Dist: requests ==2.28.1
Requires-Dist: cachetools
Requires-Dist: varname
Requires-Dist: asttokens
Requires-Dist: pure-eval
Requires-Dist: Werkzeug ==2.2.2
Requires-Dist: waitress
